Metadata-Version: 1.0
Name: sodacan
Version: 0.0.4
Summary: UNKNOWN
Home-page: UNKNOWN
Author: apps
Author-email: apps@appsappsapps.com
License: Python. Donate To The Author `3GzCiEb8K4V29D4tgPq5Y5fXHHiqewzGvu` to use with attribution required.
Platform: UNKNOWN
